MANIFEST.in
requirements.txt
setup.cfg
setup.py
aj/__init__.py
aj/auth.py
aj/compat.py
aj/config.py
aj/core.py
aj/entry.py
aj/http.py
aj/https_redirect.py
aj/log.py
aj/plugins.py
aj/routing.py
aj/wsgi.py
aj.egg-info/PKG-INFO
aj.egg-info/SOURCES.txt
aj.egg-info/dependency_links.txt
aj.egg-info/requires.txt
aj.egg-info/top_level.txt
aj/api/__init__.py
aj/api/endpoint.py
aj/api/http.py
aj/api/mail.py
aj/gate/__init__.py
aj/gate/gate.py
aj/gate/middleware.py
aj/gate/session.py
aj/gate/stream.py
aj/gate/worker.py
aj/security/__init__.py
aj/security/pwreset.py
aj/security/totp.py
aj/security/verifier.py
aj/static/emails/reset_email.html
aj/static/images/Logo.png
aj/static/images/error.jpeg
aj/util/__init__.py
aj/util/broadcast_queue.py
aj/util/lazy.py
aj/util/misc.py
aj/util/pidfile.py
aj/util/public.py
aj/util/strings.py