Metadata-Version: 2.4
Name: aj
Version: 2.2.11
Summary: Web UI base toolkit
Home-page: https://ajenti.org/
Author: Eugene Pankov
Author-email: e@ajenti.org
Requires-Python: >=3
Requires-Dist: arrow
Requires-Dist: bs4
Requires-Dist: cookies
Requires-Dist: cryptography
Requires-Dist: distro
Requires-Dist: greenlet>=2.0.2
Requires-Dist: gevent<=25.4.2
Requires-Dist: gevent-websocket
Requires-Dist: gipc==1.8.0
Requires-Dist: itsdangerous
Requires-Dist: jadi>=1.0.3
Requires-Dist: jinja2
Requires-Dist: lxml>=2.2.4
Requires-Dist: passlib
Requires-Dist: pexpect
Requires-Dist: psutil>=2.2.1
Requires-Dist: pyOpenSSL
Requires-Dist: pyotp
Requires-Dist: python-daemon
Requires-Dist: python-socketio==5.8.0
Requires-Dist: python-engineio==4.4.1
Requires-Dist: pyyaml
Requires-Dist: qrcode
Requires-Dist: reconfigure
Requires-Dist: requests>=2
Requires-Dist: setproctitle
Requires-Dist: simplejson
Requires-Dist: six>=1.9.0
Requires-Dist: termcolor
Requires-Dist: pip>=20
Requires-Dist: setuptools>=41
Requires-Dist: gevent>=1
Dynamic: author
Dynamic: author-email
Dynamic: home-page
Dynamic: requires-dist
Dynamic: requires-python
Dynamic: summary
